prism/__init__.py
prism/admin.py
prism/constants.py
prism/exceptions.py
prism/logging.py
prism/main.py
prism/target.py
prism/task.py
prism/ui.py
prism/agents/__init__.py
prism/agents/base.py
prism/agents/docker_agent.py
prism/agents/ec2.py
prism/agents/meta.py
prism/agents/scripts/__init__.py
prism/agents/scripts/apply.sh
prism/agents/scripts/run.sh
prism/cli/__init__.py
prism/cli/agent.py
prism/cli/base.py
prism/cli/compile.py
prism/cli/connect.py
prism/cli/create_agent.py
prism/cli/create_task.py
prism/cli/create_trigger.py
prism/cli/graph.py
prism/cli/init.py
prism/cli/run.py
prism/cli/spark_submit.py
prism/client/__init__.py
prism/decorators/__init__.py
prism/decorators/target.py
prism/decorators/task.py
prism/docs/__init__.py
prism/docs/build/311ea03002abadcdcaba.png
prism/docs/build/54968a39190c43d592b9.svg
prism/docs/build/737ad70b3f2d3a9b5f6e.ico
prism/docs/build/__init__.py
prism/docs/build/ce188596011a8fa32931.png
prism/docs/build/index.html
prism/docs/build/main.js.LICENSE.txt
prism/event_managers/__init__.py
prism/event_managers/base.py
prism/infra/__init__.py
prism/infra/compiler.py
prism/infra/executor.py
prism/infra/hooks.py
prism/infra/manifest.py
prism/infra/module.py
prism/infra/pipeline.py
prism/infra/project.py
prism/infra/sys_path.py
prism/infra/task_manager.py
prism/mixins/__init__.py
prism/mixins/agent.py
prism/mixins/aws.py
prism/mixins/base.py
prism/mixins/compile.py
prism/mixins/connect.py
prism/mixins/create_agent.py
prism/mixins/create_task.py
prism/mixins/create_trigger.py
prism/mixins/graph.py
prism/mixins/run.py
prism/mixins/sys_handler.py
prism/parsers/__init__.py
prism/parsers/ast_parser.py
prism/parsers/base.py
prism/parsers/yml_parser.py
prism/profiles/__init__.py
prism/profiles/adapter.py
prism/profiles/bigquery.py
prism/profiles/dbt.py
prism/profiles/meta.py
prism/profiles/postgres.py
prism/profiles/profile.py
prism/profiles/pyspark.py
prism/profiles/redshift.py
prism/profiles/snowflake.py
prism/profiles/trino.py
prism_dev-0.1.2.dist-info/LICENSE
prism_dev-0.1.2.dist-info/METADATA
prism_dev-0.1.2.dist-info/WHEEL
prism_dev-0.1.2.dist-info/entry_points.txt
prism_dev-0.1.2.dist-info/top_level.txt
prism_dev-0.1.2.dist-info/RECORD
