Metadata-Version: 2.1
Name: prism-dev
Version: 0.1.2
Summary: The easiest way to create data pipelines in Python.
Author: prism founders
Author-email: hello@runprism.com
License: Apache-2.0
Project-URL: homepage, https://www.runprism.com
Project-URL: documentation, https://docs.runprism.com
Project-URL: repository, https://github.com/runprism/prism
Platform: unix
Platform: linux
Platform: osx
Platform: win32
Classifier: Programming Language :: Python :: 3
Classifier: Programming Language :: Python :: 3.7
Classifier: Programming Language :: Python :: 3.8
Classifier: Programming Language :: Python :: 3.9
Classifier: Programming Language :: Python :: 3.10
Requires-Python: >=3.7
License-File: LICENSE
Requires-Dist: astor (>=0.7)
Requires-Dist: boto3 (>=1)
Requires-Dist: botocore (>=1)
Requires-Dist: click (>=8)
Requires-Dist: networkx (>=2)
Requires-Dist: numpy (>=1)
Requires-Dist: pandas (>=1)
Requires-Dist: PyYAML (>=6)
Requires-Dist: requests (>=2)
Requires-Dist: Jinja2 (==3.1.2)
Requires-Dist: MarkupSafe (>=2.0)
Requires-Dist: coolname (>=2.2)
Requires-Dist: shortuuid (>=1.0)
Requires-Dist: rich-argparse (>=1.1.0)
Provides-Extra: bigquery
Requires-Dist: google-api-python-client (>=2) ; extra == 'bigquery'
Requires-Dist: google-auth (>=2) ; extra == 'bigquery'
Requires-Dist: google-cloud-bigquery (>=2) ; extra == 'bigquery'
Requires-Dist: db-dtypes (>=1) ; extra == 'bigquery'
Provides-Extra: dbt
Requires-Dist: dbt-core (>=1) ; extra == 'dbt'
Provides-Extra: docker
Requires-Dist: docker (>=6.0) ; extra == 'docker'
Provides-Extra: postgres
Requires-Dist: psycopg2-binary (>=2.9) ; extra == 'postgres'
Provides-Extra: pyspark
Requires-Dist: pyspark (>=3) ; extra == 'pyspark'
Provides-Extra: redshift
Requires-Dist: psycopg2-binary (>=2.9) ; extra == 'redshift'
Provides-Extra: snowflake
Requires-Dist: snowflake-connector-python (>=2) ; extra == 'snowflake'
Requires-Dist: pyarrow (<10.1.0,>=10.0.1) ; extra == 'snowflake'
Provides-Extra: testing
Requires-Dist: dbt-snowflake (>=1) ; extra == 'testing'
Requires-Dist: pytest (>=7) ; extra == 'testing'
Requires-Dist: fastparquet (<1,>=0.8) ; extra == 'testing'
Requires-Dist: tox (>=3.24) ; extra == 'testing'
Provides-Extra: trino
Requires-Dist: trino (>=0.319) ; extra == 'trino'
